Metadata-Version: 2.1
Name: google-apple-inapp-purchases
Version: 0.6
Summary: Manage in-app purchases for Apple AppStore and Google Play
Home-page: https://github.com/adanmauri/inapp-purchases.git
Author: Adán Mauri Ungaro
Author-email: adan.mauri@gmail.com
License: Apache License Version 2.0
Keywords: python in-app payment payments purchase purchases google play apple appstore iphone android
Platform: UNKNOWN
Classifier: License :: OSI Approved :: Apache Software License
Classifier: Operating System :: OS Independent
